pydgraph/__init__.py
pydgraph/async_client.py
pydgraph/async_client_stub.py
pydgraph/async_txn.py
pydgraph/client.py
pydgraph/client_stub.py
pydgraph/convert.py
pydgraph/errors.py
pydgraph/meta.py
pydgraph/retry.py
pydgraph/txn.py
pydgraph/util.py
pydgraph/proto/__init__.py
pydgraph/proto/api_pb2.py
pydgraph/proto/api_pb2.pyi
pydgraph/proto/api_pb2_grpc.py
pydgraph/proto/api_pb2_grpc.pyi
pydgraph-25.1.0.dist-info/licenses/LICENSE
pydgraph-25.1.0.dist-info/METADATA
pydgraph-25.1.0.dist-info/WHEEL
pydgraph-25.1.0.dist-info/top_level.txt
pydgraph-25.1.0.dist-info/RECORD
