Metadata-Version: 2.4
Name: pydgraph
Version: 25.1.0
Summary: Official Dgraph client implementation for Python
Author-email: "Istari Digital, Inc." <dgraph-admin@istaridigital.com>
License-Expression: Apache-2.0
Project-URL: Homepage, https://github.com/dgraph-io/pydgraph
Classifier: Intended Audience :: Developers
Classifier: Operating System :: OS Independent
Classifier: Topic :: Database
Classifier: Topic :: Software Development
Classifier: Programming Language :: Python :: 3.9
Classifier: Programming Language :: Python :: 3.10
Classifier: Programming Language :: Python :: 3.11
Classifier: Programming Language :: Python :: 3.12
Classifier: Programming Language :: Python :: 3.13
Classifier: Programming Language :: Python :: 3.14
Requires-Python: >=3.9
License-File: LICENSE
Requires-Dist: grpcio<2.0.0,>=1.65.0
Requires-Dist: protobuf<7.0.0,>=4.23.0
Provides-Extra: dev
Requires-Dist: build>=1.2.2.post1; extra == "dev"
Requires-Dist: grpcio-tools>=1.66.2; extra == "dev"
Requires-Dist: pytest>=8.3.3; extra == "dev"
Requires-Dist: pytest-asyncio>=0.23.0; extra == "dev"
Requires-Dist: ruff>=0.8.4; extra == "dev"
Requires-Dist: ty>=0.0.8; extra == "dev"
Dynamic: license-file
